{
  "us": [
    {
      "name": "ロッキード・マーティン",
      "ticker": "LMT",
      "price": "$628.70",
      "change": "+2.3%",
      "ytd": "+19.7%",
      "note": "F-35戦闘機、ミサイル防衛。バックログ$1,790億。PAC-3/MSE245発受注。トランプ$1.5兆国防予算で恩恵"
    },
    {
      "name": "RTX（旧レイセオン）",
      "ticker": "RTX",
      "price": "$195.19",
      "change": "+1.8%",
      "ytd": "+16.5%",
      "note": "パトリオットミサイル、航空エンジン。受注残$2,510億で過去最高"
    },
    {
      "name": "ノースロップ・グラマン",
      "ticker": "NOC",
      "price": "$698.02",
      "change": "+4.0%",
      "ytd": "+22.1%",
      "note": "B-21爆撃機、宇宙システム。アナリスト筆頭推奨。FCF $31-35億見通し"
    },
    {
      "name": "ジェネラル・ダイナミクス",
      "ticker": "GD",
      "price": "$360.10",
      "change": "+1.2%",
      "ytd": "+12.8%",
      "note": "戦車、潜水艦、ビジネスジェット。トランプ配当・自社株買い制限発言で一時下落"
    },
    {
      "name": "L3ハリス",
      "ticker": "LHX",
      "price": "$350.60",
      "change": "+0.8%",
      "ytd": "+10.2%",
      "note": "通信・電子戦システム"
    }
  ],
  "jp": [
    {
      "name": "三菱重工業",
      "code": "7011",
      "price": "¥5,152",
      "change": "+3.5%",
      "ytd": "+48.2%",
      "note": "上場来高値更新！3Q営業利益+25.5%増の3,012億円。通期予想上方修正。防衛予算増の最大受益者"
    },
    {
      "name": "川崎重工業",
      "code": "7012",
      "price": "¥7,850",
      "change": "+2.1%",
      "ytd": "+42.5%",
      "note": "3Q売上+10.9%増。潜水艦、哨戒機、ヘリコプター。エネルギーソリューション好調"
    },
    {
      "name": "IHI",
      "code": "7013",
      "price": "¥12,500",
      "change": "+2.8%",
      "ytd": "+55.3%",
      "note": "最高値更新中！航空エンジンが成長の要。3Q営業利益1,025億円。アナリスト目標株価¥13,265"
    },
    {
      "name": "日本製鋼所",
      "code": "5631",
      "price": "¥6,200",
      "change": "+3.1%",
      "ytd": "+68.5%",
      "note": "戦車砲、防弾板、火薬。防衛費増額の恩恵大"
    },
    {
      "name": "NEC",
      "code": "6701",
      "price": "¥15,200",
      "change": "+1.2%",
      "ytd": "+28.6%",
      "note": "防衛通信システム、サイバーセキュリティ"
    }
  ]
}
